polyflin/BOSS2CHARMM.py
polyflin/BOSS2DESMOND.py
polyflin/BOSS2GMX.py
polyflin/BOSS2LAMMPS.py
polyflin/BOSS2OPENMM.py
polyflin/BOSS2Q.py
polyflin/BOSS2TINKER.py
polyflin/BOSS2XPLOR.py
polyflin/BOSSReader.py
polyflin/Orca2CM5charges.py
polyflin/Vector_algebra.py
polyflin/__init__.py
polyflin/createZmat.py
polyflin/fepzmat.py
polyflin/mol_boss.py
polyflin/polyflin.py
polyflin-2.0.3.dist-info/LICENSE
polyflin-2.0.3.dist-info/METADATA
polyflin-2.0.3.dist-info/WHEEL
polyflin-2.0.3.dist-info/entry_points.txt
polyflin-2.0.3.dist-info/top_level.txt
polyflin-2.0.3.dist-info/RECORD
