Metadata-Version: 2.1
Name: polyflin
Version: 2.0.3
Summary: A powerful pyhton module for multiconfiguration polymer structure generation
Author-email: "Abd. Kakhar Umar" <abdulkaharumar@gmail.com>
Project-URL: Homepage, https://etflin.com/software/PolyFlin
Project-URL: Bug Tracker, https://etflin.com/software/PolyFlin
Keywords: polymer,topology,chemistry
Classifier: Programming Language :: Python :: 3
Classifier: License :: OSI Approved :: MIT License
Classifier: Operating System :: OS Independent
Classifier: Topic :: Scientific/Engineering :: Chemistry
Classifier: Topic :: Scientific/Engineering :: Bio-Informatics
Requires-Python: >=3.7
License-File: LICENSE
Requires-Dist: rdkit
Requires-Dist: numpy
Requires-Dist: panda
Requires-Dist: networkx
